Workbook

Sheet Inputs
A1: PAPERHINT — PRICING INPUTS
A2: Edit only the yellow cells. Everything else recalculates.
A4: School profile (sample: mid-size school)
A5: Students | B5: 1000 | C5: Total enrolled students
A6: Teachers | B6: 40 | C6: Teaching staff with active accounts
A7: Subjects | B7: 12 | C7: Subjects with knowledge base / library maintained
A9: Unit maintenance cost (₹ per year) — assumptions, not quotes
A10: Cost per student / year | B10: 30 | C10: Hosting + records/marks storage + ~150 parent emails (₹0.07/email). Assumption by Shrivathsan/Claude — validate against real cloud bills.
A11: Cost per teacher / year | B11: 400 | C11: Heavier usage: question-paper generation, notes, content & AI features. Assumption — AI usage is the swing factor.
A12: Cost per subject / year | B12: 300 | C12: Digital library & knowledge-base storage, indexing, backup per subject. Assumption.
A13: School base cost / year | B13: 40000 | C13: Fixed per school: base infra, support share, amortised onboarding. Assumption — set to 0 to match the pure teacher+student+subject formula.
A15: Margin
A16: Margin (% of overall cost) | B16: 0.5 | C16: Your formula: price = cost + 50% of cost (a markup). Note: a true 50% GROSS margin would be price = cost ÷ 0.5.
A19: Legend
A20: Yellow + blue text = edit these · Black = calculated · Green = pulls from another sheet
A21: All ₹ figures are illustrative placeholders supplied in this working session, not researched market rates.

Sheet Cost Model
A1: COST MODEL — price per student
A2: [ operation cost = teachers + students + subjects (+ school base) ] + margin = price per student
A4: Operation cost (₹ / year)
A5: Students cost | B5: =Inputs!B5*Inputs!B10 -> 30000 | E5: students × cost per student
A6: Teachers cost | B6: =Inputs!B6*Inputs!B11 -> 16000 | E6: teachers × cost per teacher
A7: Subjects maintenance cost | B7: =Inputs!B7*Inputs!B12 -> 3600 | E7: subjects × cost per subject
A8: School base cost | B8: =Inputs!B13 -> 40000 | E8: fixed per school
A9: Total operation cost | B9: =SUM(B5:B8) -> 89600
A11: Per-student economics (₹ / year)
A12: Operation cost per student | B12: =B9/Inputs!B5 -> 89.6 | E12: total operation cost ÷ students
A13: Margin (50% of cost) | B13: =B12*Inputs!B16 -> 44.8
A14: PRICE PER STUDENT / YEAR | B14: =B12+B13 -> 134.4 | E14: what the school pays per student
A15: Price per student / month | B15: =B14/12 -> 11.2 | E15: what a parent would feel per month
A17: School-level view (₹ / year)
A18: Annual revenue from school | B18: =B14*Inputs!B5 -> 134400 | E18: price × students
A19: Annual profit from school | B19: =B18-B9 -> 44800 | E19: revenue − operation cost
A20: Check: profit as % of cost | B20: =B19/B9 -> 0.5 | E20: should equal the margin % on Inputs

Sheet Scenarios
A1: SCENARIOS — same unit costs, different school sizes
A2: Edit the yellow counts; unit costs & margin pull from Inputs.
B4: Small school | C4: Mid school | D4: Large school
A5: Students | B5: 300 | C5: 1000 | D5: 2500
A6: Teachers | B6: 15 | C6: 40 | D6: 90
A7: Subjects | B7: 10 | C7: 12 | D7: 14
A9: Total operation cost | B9: =B5*Inputs!$B$10+B6*Inputs!$B$11+B7*Inputs!$B$12+Inputs!$B$13 -> 58000 | C9: =C5*Inputs!$B$10+C6*Inputs!$B$11+C7*Inputs!$B$12+Inputs!$B$13 -> 89600 | D9: =D5*Inputs!$B$10+D6*Inputs!$B$11+D7*Inputs!$B$12+Inputs!$B$13 -> 155200
A10: Cost per student / year | B10: =B9/B5 -> 193.33333 | C10: =C9/C5 -> 89.6 | D10: =D9/D5 -> 62.08
A11: Price per student / year (+margin) | B11: =B10*(1+Inputs!$B$16) -> 290 | C11: =C10*(1+Inputs!$B$16) -> 134.4 | D11: =D10*(1+Inputs!$B$16) -> 93.12
A12: Price per student / month | B12: =B11/12 -> 24.166667 | C12: =C11/12 -> 11.2 | D12: =D11/12 -> 7.76
A13: Annual revenue | B13: =B11*B5 -> 87000 | C13: =C11*C5 -> 134400 | D13: =D11*D5 -> 232800
A14: Annual profit | B14: =B13-B9 -> 29000 | C14: =C13-C9 -> 44800 | D14: =D13-D9 -> 77600
A16: Takeaway: fixed school base cost makes small schools costlier per student — price tiers or a minimum school fee cover it.
